tasker/__init__.py
tasker/cli.py
tasker/constants.py
tasker/manager.py
tasker/runners.py
tasker/utils.py
tasker_scheduler-0.1.1.dist-info/METADATA
tasker_scheduler-0.1.1.dist-info/WHEEL
tasker_scheduler-0.1.1.dist-info/entry_points.txt
tasker_scheduler-0.1.1.dist-info/top_level.txt
tasker_scheduler-0.1.1.dist-info/RECORD
