Metadata-Version: 2.4
Name: tasker_scheduler
Version: 0.1.1
Summary: Utility for running commands on intervals
Requires-Python: >=3.12
Requires-Dist: psutil>=7.1.3
Requires-Dist: pyyaml>=6.0.3
Requires-Dist: typer>=0.20.0
